libname/__init__.py
libname/hello.py
mjhelloworldsawesome1-0.0.14.dist-info/METADATA
mjhelloworldsawesome1-0.0.14.dist-info/WHEEL
mjhelloworldsawesome1-0.0.14.dist-info/top_level.txt
mjhelloworldsawesome1-0.0.14.dist-info/RECORD
