Metadata-Version: 2.1
Name: mjhelloworldsawesome1
Version: 0.0.14
Summary: Streaming video data via networks
Author: NeuralNine (Florian Dedov)
Author-email: pakdel.mj@gmail.com
Keywords: python,video,stream,video stream,camera stream,sockets
Classifier: Development Status :: 1 - Planning
Classifier: Intended Audience :: Developers
Classifier: Programming Language :: Python :: 3
Classifier: Operating System :: Unix
Classifier: Operating System :: MacOS :: MacOS X
Classifier: Operating System :: Microsoft :: Windows
